booking_copilot_client/__init__.py
booking_copilot_client/client.py
booking_copilot_client-0.0.5.dist-info/METADATA
booking_copilot_client-0.0.5.dist-info/WHEEL
booking_copilot_client-0.0.5.dist-info/top_level.txt
booking_copilot_client-0.0.5.dist-info/RECORD
