Metadata-Version: 2.1
Name: booking_copilot_client
Version: 0.0.5
Requires-Dist: requests
Requires-Dist: boto3
